numerosprimospythonn/__init__.py
numerosprimospythonn-1.0.dist-info/LICENSE.txt
numerosprimospythonn-1.0.dist-info/METADATA
numerosprimospythonn-1.0.dist-info/WHEEL
numerosprimospythonn-1.0.dist-info/top_level.txt
numerosprimospythonn-1.0.dist-info/RECORD
