Metadata-Version: 2.1
Name: numerosprimospythonn
Version: 1.0
Summary: A tool to identify prime numbers.
Home-page: UNKNOWN
Author: Carlos Soto
Author-email: carlosmanuelsotodefreitas@gmail.com
License: GNU GPLv3
Keywords: mathematical operations
Platform: UNKNOWN
Classifier: Development Status :: 3 - Alpha
Classifier: Intended Audience :: Developers
Classifier: Topic :: Utilities
Classifier: License :: OSI Approved :: GNU General Public License v3 (GPLv3)
Classifier: Programming Language :: Python :: 3
Classifier: Operating System :: OS Independent
License-File: LICENSE.txt
